goat_plugins/lulo/__init__.py
goat_plugins/lulo/parameters.py
goat_plugins/lulo/service.py
goat_sdk_plugin_lulo-0.1.1.dist-info/METADATA
goat_sdk_plugin_lulo-0.1.1.dist-info/WHEEL
goat_sdk_plugin_lulo-0.1.1.dist-info/RECORD
