Metadata-Version: 2.3
Name: goat-sdk-plugin-lulo
Version: 0.1.1
Summary: Goat plugin for lulo
Keywords: goat,sdk,agents,ai,lulo
Author: Andrea Villa
Author-email: andreakarimodm@gmail.com
Requires-Python: >=3.10,<4.0
Classifier: Programming Language :: Python :: 3
Classifier: Programming Language :: Python :: 3.10
Classifier: Programming Language :: Python :: 3.11
Classifier: Programming Language :: Python :: 3.12
Classifier: Programming Language :: Python :: 3.13
Requires-Dist: aiohttp (>=3.8.6,<4.0.0)
Requires-Dist: goat-sdk (>=0.1.0,<0.2.0)
Requires-Dist: goat-sdk-wallet-solana (>=0.1.1,<0.2.0)
Requires-Dist: python-dotenv (>=1.0.0,<2.0.0)
Project-URL: Bug Tracker, https://github.com/goat-sdk/goat/issues
Project-URL: Homepage, https://ohmygoat.dev/
Project-URL: Repository, https://github.com/goat-sdk/goat
